ballchaser/__init__.py
ballchaser/client.py
ballchaser-0.8.0.dist-info/LICENSE
ballchaser-0.8.0.dist-info/WHEEL
ballchaser-0.8.0.dist-info/METADATA
ballchaser-0.8.0.dist-info/RECORD
