Metadata-Version: 2.1
Name: ballchaser
Version: 0.8.0
Summary: Unofficial Python API client for the ballchasing.com API.
Home-page: https://github.com/tom-boyes-park/ballchaser
License: MIT
Author: Tom Boyes-Park
Requires-Python: >=3.7,<4.0
Classifier: License :: OSI Approved :: MIT License
Classifier: Programming Language :: Python :: 3
Classifier: Programming Language :: Python :: 3.10
Classifier: Programming Language :: Python :: 3.7
Classifier: Programming Language :: Python :: 3.8
Classifier: Programming Language :: Python :: 3.9
Requires-Dist: backoff (>=1.11.1,<2.0.0)
Requires-Dist: requests (>=2.27.1,<3.0.0)
Project-URL: Repository, https://github.com/tom-boyes-park/ballchaser
